mystats_zzh/__init__.py
mystats_zzh/data_processor.py
mystats_zzh/rank_sum.py
mystats_zzh/t_test.py
mystats_zzh/data_tables/rank_table.json
mystats_zzh/data_tables/t_table.json
mystats_zzh/data_tables/z_table.json
mystats_zzh-1.0.1.dist-info/METADATA
mystats_zzh-1.0.1.dist-info/WHEEL
mystats_zzh-1.0.1.dist-info/top_level.txt
mystats_zzh-1.0.1.dist-info/RECORD
