Metadata-Version: 2.4
Name: mystats_zzh
Version: 1.0.1
Summary: 统计假设检验工具包（秩和检验/t检验）
Author-email: zzh <zhaochenxian@outlook.com>
License: MIT
Classifier: Programming Language :: Python :: 3
Classifier: License :: OSI Approved :: MIT License
Classifier: Topic :: Scientific/Engineering :: Mathematics
